{
  "DataContractVersion": "1.1",
  "DocumentTypes": [
    {
      "DocumentTypeId": "SampleGroup.SampleCategory.Invoice",
      "Group": "SampleGroup",
      "Category": "SampleCategory",
      "Name": "Invoice",
      "OptionalUniqueIdentifier": null,
      "TypeField": {
        "FieldId": "SampleGroup.SampleCategory.Invoice.DocumentType",
        "FieldName": "Document Type"
      },
      "Fields": [
        {
          "FieldId": "SampleGroup.SampleCategory.Invoice.Username",
          "FieldName": "Username",
          "IsMultiValue": false,
          "Type": "Text",
          "DeriveFieldsFormat": "",
          "Components": [],
          "SetValues": [],
          "Metadata": [
            {
              "Key": "RequiresReference",
              "Value": "true"
            }
          ]
        },
        {
          "FieldId": "SampleGroup.SampleCategory.Invoice.InvoiceNumber",
          "FieldName": "Invoice Number",
          "IsMultiValue": false,
          "Type": "Number",
          "DeriveFieldsFormat": "",
          "Components": [],
          "SetValues": [],
          "Metadata": [
            {
              "Key": "RequiresReference",
              "Value": "true"
            }
          ]
        },
        {
          "FieldId": "SampleGroup.SampleCategory.Invoice.PlanDetails",
          "FieldName": "Plan Details",
          "IsMultiValue": false,
          "Type": "Table",
          "DeriveFieldsFormat": "",
          "Components": [
            {
              "FieldId": "SampleGroup.SampleCategory.Invoice.PlanDetails.PlanDescription",
              "FieldName": "Plan Description",
              "IsMultiValue": false,
              "Type": "Text",
              "DeriveFieldsFormat": "",
              "Components": [],
              "SetValues": [],
              "Metadata": [
                {
                  "Key": "RequiresReference",
                  "Value": "true"
                }
              ]
            },
            {
              "FieldId": "SampleGroup.SampleCategory.Invoice.PlanDetails.Rate",
              "FieldName": "Rate",
              "IsMultiValue": false,
              "Type": "Number",
              "DeriveFieldsFormat": "",
              "Components": [],
              "SetValues": [],
              "Metadata": [
                {
                  "Key": "RequiresReference",
                  "Value": "true"
                }
              ]
            }
          ],
          "SetValues": [],
          "Metadata": [
            {
              "Key": "RequiresReference",
              "Value": "true"
            }
          ]
        }
      ]
    },
    {
      "DocumentTypeId": "SampleGroup.SampleCategory.MedicalPrescription",
      "Group": "SampleGroup",
      "Category": "SampleCategory",
      "Name": "Medical Prescription",
      "OptionalUniqueIdentifier": null,
      "TypeField": {
        "FieldId": "SampleGroup.SampleCategory.MedicalPrescription.DocumentType",
        "FieldName": "Document Type"
      },
      "Fields": [
        {
          "FieldId": "SampleGroup.SampleCategory.MedicalPrescription.PatientName",
          "FieldName": "Patient Name",
          "IsMultiValue": false,
          "Type": "Text",
          "DeriveFieldsFormat": "",
          "Components": [],
          "SetValues": [],
          "Metadata": [
            {
              "Key": "RequiresReference",
              "Value": "true"
            }
          ]
        },
        {
          "FieldId": "SampleGroup.SampleCategory.MedicalPrescription.PatientAge",
          "FieldName": "Patient Age",
          "IsMultiValue": false,
          "Type": "Number",
          "DeriveFieldsFormat": "",
          "Components": [],
          "SetValues": [],
          "Metadata": [
            {
              "Key": "RequiresReference",
              "Value": "true"
            }
          ]
        },
        {
          "FieldId": "SampleGroup.SampleCategory.MedicalPrescription.Date",
          "FieldName": "Date",
          "IsMultiValue": false,
          "Type": "Date",
          "DeriveFieldsFormat": "",
          "Components": [],
          "SetValues": [],
          "Metadata": [
            {
              "Key": "RequiresReference",
              "Value": "true"
            }
          ]
        },
        {
          "FieldId": "SampleGroup.SampleCategory.MedicalPrescription.DoctorName",
          "FieldName": "Doctor Name",
          "IsMultiValue": false,
          "Type": "Text",
          "DeriveFieldsFormat": "",
          "Components": [],
          "SetValues": [],
          "Metadata": [
            {
              "Key": "RequiresReference",
              "Value": "true"
            }
          ]
        },
        {
          "FieldId": "SampleGroup.SampleCategory.MedicalPrescription.MedicalCentreName",
          "FieldName": "Medical Centre Name",
          "IsMultiValue": false,
          "Type": "Text",
          "DeriveFieldsFormat": "",
          "Components": [],
          "SetValues": [],
          "Metadata": [
            {
              "Key": "RequiresReference",
              "Value": "true"
            }
          ]
        },
        {
          "FieldId": "SampleGroup.SampleCategory.MedicalPrescription.PrescriptionDetails",
          "FieldName": "Prescription Details",
          "IsMultiValue": false,
          "Type": "Text",
          "DeriveFieldsFormat": "",
          "Components": [],
          "SetValues": [],
          "Metadata": [
            {
              "Key": "RequiresReference",
              "Value": "true"
            }
          ]
        }
      ]
    }
  ],
  "Groups": [
    {
      "Name": "SampleGroup",
      "Categories": [
        "SampleCategory"
      ]
    }
  ],
  "SupportedLanguages": [
    {
      "Name": "Undetermined Language",
      "Code": "und"
    },
    {
      "Name": "Bulgarian",
      "Code": "bul"
    },
    {
      "Name": "Cantonese",
      "Code": "yue"
    },
    {
      "Name": "Danish",
      "Code": "dan"
    },
    {
      "Name": "Dutch",
      "Code": "nld"
    },
    {
      "Name": "English",
      "Code": "eng"
    },
    {
      "Name": "French",
      "Code": "fra"
    },
    {
      "Name": "Georgian",
      "Code": "kat"
    },
    {
      "Name": "German",
      "Code": "deu"
    },
    {
      "Name": "Greek",
      "Code": "ell"
    },
    {
      "Name": "Hebrew",
      "Code": "heb"
    },
    {
      "Name": "Hindi",
      "Code": "hin"
    },
    {
      "Name": "Italian",
      "Code": "ita"
    },
    {
      "Name": "Japanese",
      "Code": "jpn"
    },
    {
      "Name": "Korean",
      "Code": "kor"
    },
    {
      "Name": "Macedonian",
      "Code": "mkd"
    },
    {
      "Name": "Mandarin",
      "Code": "zho"
    },
    {
      "Name": "Marathi",
      "Code": "mar"
    },
    {
      "Name": "Norwegian",
      "Code": "nor"
    },
    {
      "Name": "Polish",
      "Code": "pol"
    },
    {
      "Name": "Portuguese",
      "Code": "por"
    },
    {
      "Name": "Romanian",
      "Code": "ron"
    },
    {
      "Name": "Russian",
      "Code": "rus"
    },
    {
      "Name": "Serbian",
      "Code": "srp"
    },
    {
      "Name": "Spanish",
      "Code": "spa"
    },
    {
      "Name": "Swedish",
      "Code": "swe"
    },
    {
      "Name": "Telugu",
      "Code": "tel"
    }
  ]
}